fundoshi/__init__.py
fundoshi/classes.py
fundoshi/exceptions.py
fundoshi/main.py
fundoshi/sites/__init__.py
fundoshi/sites/mangapanda.py
fundoshi/sites/utils.py
fundoshi/sites/kissmanga/__init__.py
fundoshi/sites/kissmanga/decoder.py
fundoshi/sites/kissmanga/main.py
fundoshi/tests/__init__.py
fundoshi/tests/test_kissmanga.py
fundoshi/tests/test_mangapanda.py
fundoshi-0.0.8.dist-info/DESCRIPTION.rst
fundoshi-0.0.8.dist-info/METADATA
fundoshi-0.0.8.dist-info/RECORD
fundoshi-0.0.8.dist-info/WHEEL
fundoshi-0.0.8.dist-info/metadata.json
fundoshi-0.0.8.dist-info/top_level.txt
