Metadata-Version: 2.0
Name: fundoshi
Version: 0.0.8
Summary: Get manga series & chapter data from various reader sites.
Home-page: http://github.com/nhanb/fundoshi
Author: Bùi Thành Nhân
Author-email: nhan@nerdyweekly.com
License: MIT
Platform: UNKNOWN
Classifier: Development Status :: 2 - Pre-Alpha
Classifier: Intended Audience :: Developers
Classifier: Natural Language :: English
Classifier: License :: OSI Approved :: MIT License
Classifier: Operating System :: OS Independent
Classifier: Programming Language :: Python
Classifier: Programming Language :: Python :: 3
Classifier: Programming Language :: Python :: 3.4
Classifier: Programming Language :: Python :: 3.5
Classifier: Programming Language :: Python :: 3.6
Classifier: Topic :: Software Development :: Libraries :: Python Modules
Requires-Dist: beautifulsoup4
Requires-Dist: cfscrape
Requires-Dist: pycrypto
Requires-Dist: requests
